{
	"partitions" : [
		{
			"name" : "Top",
			"pins" : [
				{
					"name" : "rs",
					"strict" : false
				},
				{
					"name" : "en",
					"strict" : false
				},
				{
					"name" : "lcd_data[0]",
					"strict" : false
				},
				{
					"name" : "lcd_data[1]",
					"strict" : false
				},
				{
					"name" : "lcd_data[2]",
					"strict" : false
				},
				{
					"name" : "lcd_data[3]",
					"strict" : false
				},
				{
					"name" : "lcd_data[4]",
					"strict" : false
				},
				{
					"name" : "lcd_data[5]",
					"strict" : false
				},
				{
					"name" : "lcd_data[6]",
					"strict" : false
				},
				{
					"name" : "lcd_data[7]",
					"strict" : false
				},
				{
					"name" : "show_entries",
					"strict" : false
				},
				{
					"name" : "reset",
					"strict" : false
				},
				{
					"name" : "entry_1[11]",
					"strict" : false
				},
				{
					"name" : "entry_1[7]",
					"strict" : false
				},
				{
					"name" : "entry_1[3]",
					"strict" : false
				},
				{
					"name" : "entry_1[15]",
					"strict" : false
				},
				{
					"name" : "entry_1[9]",
					"strict" : false
				},
				{
					"name" : "entry_1[5]",
					"strict" : false
				},
				{
					"name" : "entry_1[1]",
					"strict" : false
				},
				{
					"name" : "entry_1[13]",
					"strict" : false
				},
				{
					"name" : "entry_1[4]",
					"strict" : false
				},
				{
					"name" : "entry_1[8]",
					"strict" : false
				},
				{
					"name" : "entry_1[0]",
					"strict" : false
				},
				{
					"name" : "entry_1[12]",
					"strict" : false
				},
				{
					"name" : "entry_1[6]",
					"strict" : false
				},
				{
					"name" : "entry_1[10]",
					"strict" : false
				},
				{
					"name" : "entry_1[2]",
					"strict" : false
				},
				{
					"name" : "entry_1[14]",
					"strict" : false
				},
				{
					"name" : "clock",
					"strict" : false
				}
			]
		}
	]
}